__init__.py
file_exporter_api_python_sdk-1.0.1.dist-info/licenses/LICENSE
fmconsult/__init__.py
fmconsult/fileexporterapi/__init__.py
fmconsult/fileexporterapi/api.py
fmconsult/fileexporterapi/apis/__init__.py
fmconsult/fileexporterapi/apis/filegenerator.py
fmconsult/fileexporterapi/apis/imagecompressor.py
fmconsult/fileexporterapi/dtos/__init__.py
fmconsult/fileexporterapi/dtos/excel.py
fmconsult/fileexporterapi/dtos/image.py
file_exporter_api_python_sdk-1.0.1.dist-info/METADATA
file_exporter_api_python_sdk-1.0.1.dist-info/WHEEL
file_exporter_api_python_sdk-1.0.1.dist-info/top_level.txt
file_exporter_api_python_sdk-1.0.1.dist-info/RECORD
